{"nodes": [{"id": "c_users_dell_desktop_jupiter_website_src_app_tsx", "label": "App.tsx", "file_type": "code", "source_file": "C:\\Users\\DELL\\Desktop\\jupiter website\\src\\App.tsx", "source_location": "L1"}, {"id": "app_app", "label": "App()", "file_type": "code", "source_file": "C:\\Users\\DELL\\Desktop\\jupiter website\\src\\App.tsx", "source_location": "L16"}], "edges": [{"source": "c_users_dell_desktop_jupiter_website_src_app_tsx", "target": "react", "relation": "imports_from", "confidence": "EXTRACTED", "source_file": "C:\\Users\\DELL\\Desktop\\jupiter website\\src\\App.tsx", "source_location": "L1", "weight": 1.0}, {"source": "c_users_dell_desktop_jupiter_website_src_app_tsx", "target": "c_users_dell_desktop_jupiter_website_src_components_providers_lenisprovider", "relation": "imports_from", "confidence": "EXTRACTED", "source_file": "C:\\Users\\DELL\\Desktop\\jupiter website\\src\\App.tsx", "source_location": "L2", "weight": 1.0}, {"source": "c_users_dell_desktop_jupiter_website_src_app_tsx", "target": "c_users_dell_desktop_jupiter_website_src_components_ui_customcursor", "relation": "imports_from", "confidence": "EXTRACTED", "source_file": "C:\\Users\\DELL\\Desktop\\jupiter website\\src\\App.tsx", "source_location": "L3", "weight": 1.0}, {"source": "c_users_dell_desktop_jupiter_website_src_app_tsx", "target": "c_users_dell_desktop_jupiter_website_src_components_ui_pagetransition", "relation": "imports_from", "confidence": "EXTRACTED", "source_file": "C:\\Users\\DELL\\Desktop\\jupiter website\\src\\App.tsx", "source_location": "L4", "weight": 1.0}, {"source": "c_users_dell_desktop_jupiter_website_src_app_tsx", "target": "c_users_dell_desktop_jupiter_website_src_components_layout_navbar", "relation": "imports_from", "confidence": "EXTRACTED", "source_file": "C:\\Users\\DELL\\Desktop\\jupiter website\\src\\App.tsx", "source_location": "L5", "weight": 1.0}, {"source": "c_users_dell_desktop_jupiter_website_src_app_tsx", "target": "c_users_dell_desktop_jupiter_website_src_components_layout_footer", "relation": "imports_from", "confidence": "EXTRACTED", "source_file": "C:\\Users\\DELL\\Desktop\\jupiter website\\src\\App.tsx", "source_location": "L6", "weight": 1.0}, {"source": "c_users_dell_desktop_jupiter_website_src_app_tsx", "target": "c_users_dell_desktop_jupiter_website_src_components_sections_introloader", "relation": "imports_from", "confidence": "EXTRACTED", "source_file": "C:\\Users\\DELL\\Desktop\\jupiter website\\src\\App.tsx", "source_location": "L7", "weight": 1.0}, {"source": "c_users_dell_desktop_jupiter_website_src_app_tsx", "target": "c_users_dell_desktop_jupiter_website_src_components_sections_hero", "relation": "imports_from", "confidence": "EXTRACTED", "source_file": "C:\\Users\\DELL\\Desktop\\jupiter website\\src\\App.tsx", "source_location": "L8", "weight": 1.0}, {"source": "c_users_dell_desktop_jupiter_website_src_app_tsx", "target": "c_users_dell_desktop_jupiter_website_src_components_sections_painpoints", "relation": "imports_from", "confidence": "EXTRACTED", "source_file": "C:\\Users\\DELL\\Desktop\\jupiter website\\src\\App.tsx", "source_location": "L9", "weight": 1.0}, {"source": "c_users_dell_desktop_jupiter_website_src_app_tsx", "target": "c_users_dell_desktop_jupiter_website_src_components_sections_cases", "relation": "imports_from", "confidence": "EXTRACTED", "source_file": "C:\\Users\\DELL\\Desktop\\jupiter website\\src\\App.tsx", "source_location": "L10", "weight": 1.0}, {"source": "c_users_dell_desktop_jupiter_website_src_app_tsx", "target": "c_users_dell_desktop_jupiter_website_src_components_sections_services", "relation": "imports_from", "confidence": "EXTRACTED", "source_file": "C:\\Users\\DELL\\Desktop\\jupiter website\\src\\App.tsx", "source_location": "L11", "weight": 1.0}, {"source": "c_users_dell_desktop_jupiter_website_src_app_tsx", "target": "c_users_dell_desktop_jupiter_website_src_components_sections_testimonials", "relation": "imports_from", "confidence": "EXTRACTED", "source_file": "C:\\Users\\DELL\\Desktop\\jupiter website\\src\\App.tsx", "source_location": "L13", "weight": 1.0}, {"source": "c_users_dell_desktop_jupiter_website_src_app_tsx", "target": "c_users_dell_desktop_jupiter_website_src_components_sections_ctasection", "relation": "imports_from", "confidence": "EXTRACTED", "source_file": "C:\\Users\\DELL\\Desktop\\jupiter website\\src\\App.tsx", "source_location": "L14", "weight": 1.0}, {"source": "c_users_dell_desktop_jupiter_website_src_app_tsx", "target": "app_app", "relation": "contains", "confidence": "EXTRACTED", "source_file": "C:\\Users\\DELL\\Desktop\\jupiter website\\src\\App.tsx", "source_location": "L16", "weight": 1.0}], "raw_calls": [{"caller_nid": "app_app", "callee": "useState", "source_file": "C:\\Users\\DELL\\Desktop\\jupiter website\\src\\App.tsx", "source_location": "L17"}, {"caller_nid": "app_app", "callee": "useState", "source_file": "C:\\Users\\DELL\\Desktop\\jupiter website\\src\\App.tsx", "source_location": "L18"}, {"caller_nid": "app_app", "callee": "useState", "source_file": "C:\\Users\\DELL\\Desktop\\jupiter website\\src\\App.tsx", "source_location": "L19"}, {"caller_nid": "app_app", "callee": "useCallback", "source_file": "C:\\Users\\DELL\\Desktop\\jupiter website\\src\\App.tsx", "source_location": "L26"}, {"caller_nid": "app_app", "callee": "useCallback", "source_file": "C:\\Users\\DELL\\Desktop\\jupiter website\\src\\App.tsx", "source_location": "L27"}]}